Metadata-Version: 1.0
Name: edasimplekatt
Version: 0.5
Summary: Simple exploratory data analysis
Home-page: UNKNOWN
Author: UNKNOWN
Author-email: UNKNOWN
License: UNKNOWN
Platform: UNKNOWN
